dtx/__init__.py
dtx/cli/__init__.py
dtx/cli/console.py
dtx/cli/inferencing.py
dtx/cli/utils.py
detoxio_dtx-0.2.1.dist-info/METADATA
detoxio_dtx-0.2.1.dist-info/WHEEL
detoxio_dtx-0.2.1.dist-info/entry_points.txt
detoxio_dtx-0.2.1.dist-info/RECORD
